meetup_notifier/__init__.py
meetup_notifier/meetup.py
meetup_notifier-0.1.2.dist-info/METADATA
meetup_notifier-0.1.2.dist-info/WHEEL
meetup_notifier-0.1.2.dist-info/entry_points.txt
meetup_notifier-0.1.2.dist-info/licenses/LICENSE
meetup_notifier-0.1.2.dist-info/RECORD
