Metadata-Version: 2.3
Name: meetup-notifier
Version: 0.1.2
Summary: Simple package to get information about meetups
License-File: LICENSE
Requires-Python: >=3.11
Requires-Dist: parsel>=1.9.1
Requires-Dist: requests>=2.32.3
Requires-Dist: shellingham>=1.5.4
Requires-Dist: typer>=0.12.5
